Metadata-Version: 1.0
Name: GASSBI-distributions
Version: 0.1
Summary: Gaussian distributions and binomial distribution
Home-page: UNKNOWN
Author: UNKNOWN
Author-email: UNKNOWN
License: UNKNOWN
Platform: UNKNOWN
